LICENSE
README.md
setup.py
src/install_k2/__init__.py
src/install_k2/install_k2.py
src/install_k2.egg-info/PKG-INFO
src/install_k2.egg-info/SOURCES.txt
src/install_k2.egg-info/dependency_links.txt
src/install_k2.egg-info/entry_points.txt
src/install_k2.egg-info/not-zip-safe
src/install_k2.egg-info/top_level.txt