Metadata-Version: 2.4
Name: install_k2
Version: 0.0.2
Summary: Install k2 package
Author: The Lattifai Development Team
Requires-Python: >=3.9
License-File: LICENSE
Dynamic: author
Dynamic: description
Dynamic: description-content-type
Dynamic: license-file
Dynamic: requires-python
Dynamic: summary
